ValueSelectorWidget/Widget.py
ValueSelectorWidget/__init__.py
ValueSelectorWidget_MarioRJ2002-0.0.1.dist-info/LICENSE
ValueSelectorWidget_MarioRJ2002-0.0.1.dist-info/METADATA
ValueSelectorWidget_MarioRJ2002-0.0.1.dist-info/WHEEL
ValueSelectorWidget_MarioRJ2002-0.0.1.dist-info/top_level.txt
ValueSelectorWidget_MarioRJ2002-0.0.1.dist-info/RECORD
