Metadata-Version: 2.1
Name: ValueSelectorWidget-MarioRJ2002
Version: 0.0.1
Summary: Widget selector de valores
Home-page: https://github.com/pypa/sampleproject
Author: MarioRJ2002
Author-email: marioramirez.lajarcia@gmail.com
License: UNKNOWN
Project-URL: Bug Tracker, https://github.com/pypa/sampleproject/issues
Platform: UNKNOWN
Classifier: Programming Language :: Python :: 3
Classifier: License :: OSI Approved :: MIT License
Classifier: Operating System :: OS Independent
Requires-Python: >=3.6
License-File: LICENSE
